Tarea1/Tester.v
module tester(
    output reg CLK,
    output reg RESET,
    output reg TARJETA_RECIBIDA,
    output reg DIGITO_STB,
    output reg TIPO_TRANS,
    output reg MONTO_STB,
    output reg [15:0] PIN_CORRECTO,
    output reg [3:0] DIGITO,
    output reg [63:0] BALANCE_INICIAL,
    output reg [31:0] MONTO
);

    initial CLK = 0;
    always #2 CLK = ~CLK;

    initial begin
        // Inicializacion de señales
        RESET = 0;
        TARJETA_RECIBIDA = 0;
        DIGITO_STB = 0;
        TIPO_TRANS = 0;
        MONTO_STB = 0;
        DIGITO = 4'd0;
        BALANCE_INICIAL = 64'd0;
        MONTO = 32'd0;
        PIN_CORRECTO = 16'b0011010101100110; // PIN 3566

//-----------------------------INICIO DE PRUEBA DE DEPOSITO EXITOSO------------------------------------------
        #8 RESET = 1;           // Se activa el sistema del cajero
        #4 TARJETA_RECIBIDA = 1; // La tarjeta es insertada
        #20 TARJETA_RECIBIDA = 0; // Finaliza la lectura de la tarjeta
        #4 DIGITO = 4'b0011;    // Primer dígito del PIN ingresado
        #1 DIGITO_STB = 1;      // Se marca que el dígito está disponible
        #3 DIGITO_STB = 0;      // Se desmarca la señal de dígito recibido
        #4 DIGITO = 4'b0101;    // Segundo dígito del PIN
        #1 DIGITO_STB = 1;      // Confirmación de entrada del segundo dígito
        #3 DIGITO_STB = 0;      // Señal de confirmación vuelve a cero
        #4 DIGITO = 4'b0110;    // Tercer dígito del PIN
        #1 DIGITO_STB = 1;      // Se valida la entrada del tercer dígito
        #3 DIGITO_STB = 0;      // La validación se apaga
        #4 DIGITO = 4'b0110;    // Cuarto dígito del PIN
        #1 DIGITO_STB = 1;      // Se confirma la llegada del cuarto dígito
        #3 DIGITO_STB = 0;      // Fin de la confirmación
        #2 TIPO_TRANS = 0;      // Selección de tipo de transacción: Depósito
        #4 MONTO = 32'd10000;   // Se introduce el monto: 10,000
        #2 MONTO_STB = 1;       // El monto queda registrado
        #4 MONTO_STB = 0;       // La señal de registro del monto se apaga
//-------------------------------FIN PRUEBA DE DEPOSITO EXITOSO-------------------------------------------


//-------------------------------INICIO DE PRUEBA DE RETIRO EXITOSO---------------------------------------        
	#4 TARJETA_RECIBIDA = 1;   // Señal de inserción de tarjeta -> activa
        #20 TARJETA_RECIBIDA = 0;  // Fin de la detección de tarjeta -> señal baja
        #4 DIGITO = 4'b0011;       // Entrada del primer dígito del PIN (valor binario 3)
        #4 DIGITO_STB = 1;         // Se confirma que el primer dígito está listo
        #4 DIGITO_STB = 0;         // Fin para el primer dígito
        #4 DIGITO = 4'b0101;       // Entrada del segundo dígito del PIN (valor binario 5)
        #4 DIGITO_STB = 1;         // Se confirma que el primer dígito está listo
        #4 DIGITO_STB = 0;         // Fin para el segundo dígito
        #4 DIGITO = 4'b0110;       // Entrada del tercer dígito del PIN (valor binario 6)
        #4 DIGITO_STB = 1;         // Se confirma que el tercer dígito está listo
        #4 DIGITO_STB = 0;         // Fin para el tercer digito
        #4 DIGITO = 4'b0110;       // Entrada del cuarto dígito del PIN (valor binario 6)
        #4 DIGITO_STB = 1;         // Se confirma que el cuarto dígito está listo
        #4 DIGITO_STB = 0;         // Fin para el cuarto digito 
        #4 TIPO_TRANS = 1;         // Selección del tipo de transacción: Retiro (1)
        #4 MONTO = 32'd7000;       // Se coloca el monto de la transacción
        #4 MONTO_STB = 1;          // Monto capturado por el sistema
        #4 MONTO_STB = 0;          // Fin de la señal de captura de monto
//--------------------------------FIN PRUEBA DE RETIRO EXITOSO------------------------------------------

//--------------------------------PRUEBA DE PIN INCORRECTO----------------------------------------------        
        #4 TARJETA_RECIBIDA = 1; // Se recibe la tarjeta
        #20 TARJETA_RECIBIDA = 0; // Se deja de recibir la tarjeta
        #4 DIGITO = 4'b0011; // Se recibe el primer digito
        #4 DIGITO_STB = 1; // Se indica que el digito fue recibido
        #4 DIGITO_STB = 0; // Se deja de indicar que el digito fue recibido
        #4 DIGITO = 4'b0101; // Se recibe el segundo digito
        #4 DIGITO_STB = 1; // Se indica que el digito fue recibido
        #4 DIGITO_STB = 0; // Se deja de indicar que el digito fue recibido     
        #4 DIGITO = 4'b0110; // Se recibe el tercer digito
        #4 DIGITO_STB = 1; // Se indica que el digito fue recibido
        #4 DIGITO_STB = 0; // Se deja de indicar que el digito fue recibido
        #4 DIGITO = 4'b0001; // Se recibe el cuarto digito
        #4 DIGITO_STB = 1; // Se indica que el digito fue recibido
        #4 DIGITO_STB = 0; // Se deja de indicar que el digito fue recibido
        #4 DIGITO = 4'b0001; // Se recibe el primer digito
        #4 DIGITO_STB = 1; // Se indica que el digito fue recibido
        #4 DIGITO_STB = 0; // Se deja de indicar que el digito fue recibido
        #4 DIGITO = 4'b0001; // Se recibe el segundo digito
        #4 DIGITO_STB = 1; // Se indica que el digito fue recibido
        #4 DIGITO_STB = 0; // Se deja de indicar que el digito fue recibido     
        #4 DIGITO = 4'b0001; // Se recibe el tercer digito
        #4 DIGITO_STB = 1; // Se indica que el digito fue recibido
        #4 DIGITO_STB = 0; // Se deja de indicar que el digito fue recibido
        #4 DIGITO = 4'b0001; // Se recibe el cuarto digito
        #4 DIGITO_STB = 1; // Se indica que el digito fue recibido
        #4 DIGITO_STB = 0; // Se deja de indicar que el digito fue recibido  
        #4 DIGITO = 4'b0001; // Se recibe el primer digito
        #4 DIGITO_STB = 1; // Se indica que el digito fue recibido
        #4 DIGITO_STB = 0; // Se deja de indicar que el digito fue recibido
        #4 DIGITO = 4'b0101; // Se recibe el segundo digito
        #4 DIGITO_STB = 1; // Se indica que el digito fue recibido
        #4 DIGITO_STB = 0; // Se deja de indicar que el digito fue recibido     
        #4 DIGITO = 4'b0011; // Se recibe el tercer digito
        #4 DIGITO_STB = 1; // Se indica que el digito fue recibido
        #4 DIGITO_STB = 0; // Se deja de indicar que el digito fue recibido
        #4 DIGITO = 4'b0100; // Se recibe el cuarto digito
        #4 DIGITO_STB = 1; // Se indica que el digito fue recibido
        #4 DIGITO_STB = 0; // Se deja de indicar que el digito fue recibido  
//-------------------------------FIN PRUEBA PIN INCORRECTO----------------------------------------------

//------------------------------SALIR DEL ESTADO DE BLOQUEO -------------------------
        #20 RESET = 0;        // Señal de reset activa en bajo (sistema en reinicio)
        #8  RESET = 1;        // Reset desactivado, el sistema comienza la operación normal   
//----------------------FIN DE ACCION EN ESTADO DE BLOQUEO--------------------------------------------

//----------------------INICIO DE PRUEBA DE RETIRO FALLIDO--------------------------------------------
        #10  TARJETA_RECIBIDA = 1;   // Pulso en alto: se detecta la inserción de tarjeta
        #20  TARJETA_RECIBIDA = 0;   // Fin del pulso de tarjeta, vuelve a bajo
        #4  DIGITO = 4'b0011;       // Primer dígito del PIN = 3
        #4  DIGITO_STB = 1;         // Confirma la captura del primer dígito
        #4  DIGITO_STB = 0;         // Fin de la confirmación
        #4  DIGITO = 4'b0101;       // Segundo dígito del PIN = 5
        #4  DIGITO_STB = 1;         // Pulso de validación del segundo dígito
        #4  DIGITO_STB = 0;         // Termina el pulso
        #4  DIGITO = 4'b0110;       // Tercer dígito del PIN = 6
        #4  DIGITO_STB = 1;         // Confirmación de entrada del tercer dígito
        #4  DIGITO_STB = 0;         // Señal baja, fin de validación
        #4  DIGITO = 4'b0110;       // Cuarto dígito del PIN = 6
        #4  DIGITO_STB = 1;         // Confirma el cuarto dígito
        #4  DIGITO_STB = 0;         // Pulso de confirmación finalizado
        #4  TIPO_TRANS = 1;         // Selección de transacción: 1 = Retiro
        #4  MONTO = 32'd900000;     // Se asigna monto de la transacción = 900000
        #4  MONTO_STB = 1;          // Confirma el registro del monto
        #4  MONTO_STB = 0;          // Fin del pulso
//--------------------------------FIN PRUEBA DE RETIRO FALLIDO-------------------------------------------

        #25 $finish;
    end
endmodule

Tarea1/Cajero.v
module Cajero (
    input CLK,
    input RESET,
    input TARJETA_RECIBIDA,
    input [15:0] PIN_CORRECTO, 
    input [3:0] DIGITO,
    input DIGITO_STB,
    input TIPO_TRANS,
    input [31:0] MONTO,
    input MONTO_STB,
    input [63:0] BALANCE_INICIAL,

    output reg [63:0] BALANCE_ACTUALIZADO,
    output reg BALANCE_STB,
    output reg ENTREGAR_DINERO,
    output reg FONDOS_INSUFICIENTES,
    output reg PIN_INCORRECTO,
    output reg ADVERTENCIA,
    output reg BLOQUEO
    );

    reg [1:0] intentos_fallidos;
    reg [15:0] PIN_ACTUAL;
    reg [2:0] estado;
    reg [1:0] cantidad_digitos;


    localparam ESPERANDO_TARJETA      = 3'b000, // Esperando Tarjeta
               INGRESANDO_PIN         = 3'b001, // EL usuario esta ingresando el PIN 
               ANALIZANDO_PIN         = 3'b010, // Se verifica si el PIN es correcto
               DETERMINAR_TRANSACCION = 3'b011, // El usuario elige entre retiro o depósito
               PROCESANDO_DEPOSITO    = 3'b100, // Se procesa depósito
               PROCESANDO_RETIRO      = 3'b101, // Se procesa retiro
               FIN                    = 3'b110, // Finaliza transacción
               BLOQUEADO              = 3'b111; // Tarjeta bloqueda por intentos fallidos

    always @(posedge CLK) begin
        if (!RESET) begin // si reset = 0 se inicializan todas las variables
            estado                  <= ESPERANDO_TARJETA;
	        cantidad_digitos        <= 0;
	        PIN_ACTUAL              <= 0;
	        intentos_fallidos       <= 0;
            PIN_INCORRECTO          <= 0;
            ADVERTENCIA             <= 0;
            BLOQUEO                 <= 0;
            BALANCE_STB             <= 0;
            FONDOS_INSUFICIENTES    <= 0;
            ENTREGAR_DINERO         <= 0;
            BALANCE_ACTUALIZADO     <= 0;

         
        end else begin // si reset = 1
            case (estado)
                // El sistema está esperando la tarjeta
		        ESPERANDO_TARJETA: begin
    		    // Si la señal TARJETA_RECIBIDA está activa
    		    // Cambiar al estado de INGRESANDO_PIN
    		        if (TARJETA_RECIBIDA) begin
        		        estado <= INGRESANDO_PIN;
    		        end else begin
                    // Si no hay tarjeta, permanecer en ESPERANDO_TARJETA
        		        estado <= ESPERANDO_TARJETA;
    	            end
		        end

                INGRESANDO_PIN: begin
                    // si hay un intento fallido se pone en alto PIN_INCORRECTO
                    if (intentos_fallidos == 2'd1) begin
                        PIN_INCORRECTO <= 1;
                    end else if (intentos_fallidos == 2'd2) begin
                    // si hay dos intentos fallidos se pone en alto ADVERTENCIA
                        ADVERTENCIA <= 1;
                        PIN_INCORRECTO <= 0;
                    // si hay 3 intentos fallidos se bloquea
                    end else if (intentos_fallidos == 2'd3) begin
                    	// se pasa ADVERTENCIA a 0, BLOQUEO a 1 y se cambia de estado a BLOQUEADO
                        ADVERTENCIA <= 0;
                        BLOQUEO <= 1;
                        estado <= BLOQUEADO;
                    end else begin
                    	// si no sucede, se mantiene ADVERTENCIA en cero
                        ADVERTENCIA <= 0;
                    end
                    
                    // Si DIGITO_STB = 1 e intentos fallidos es menor a 3
                    if (DIGITO_STB && (intentos_fallidos < 3)) begin
                        // cantidad_digitos funciona como un contador que indica cuántos dígitos del PIN ya se han ingresado.
                        case (cantidad_digitos) 
                            // Si cantidad_digitos es 2'b00 (o sea, 0 en decimal), ejecuta lo que está en el bloque
                            2'b00: begin
                                PIN_ACTUAL[15:12] <= DIGITO;
                                // Se actualiza cantidad_digitos
                                cantidad_digitos <= cantidad_digitos + 1;
                            end
                            2'b01: begin
                                PIN_ACTUAL[11:8] <= DIGITO;
                                cantidad_digitos <= cantidad_digitos + 1;
                            end
                            2'b10: begin
                                PIN_ACTUAL[7:4] <= DIGITO;
                                cantidad_digitos <= cantidad_digitos + 1;
                            end
                            2'b11: begin
                                PIN_ACTUAL[3:0] <= DIGITO;
                                cantidad_digitos <= 0;
                                estado <= ANALIZANDO_PIN;
                            end
                        endcase
                    end else if (intentos_fallidos < 3) begin
                        estado <= INGRESANDO_PIN;
                    end
                end

                ANALIZANDO_PIN: begin
                    // Si el pin es incorrecto entonces se activa PIN_INCORRECTO
                    if (PIN_ACTUAL != PIN_CORRECTO) begin
                    	// Se suma un intento a intentos_fallidos
                        intentos_fallidos <= intentos_fallidos + 1;
                        // Se devuelve al estado de INGRESANDO_PIN
                        estado <= INGRESANDO_PIN;
                        if (intentos_fallidos < 3) begin
                            estado <= INGRESANDO_PIN;
                        end else begin
                            estado <= BLOQUEADO;
                        end
                    end else begin
                        estado <= DETERMINAR_TRANSACCION;
                    end
                end

                DETERMINAR_TRANSACCION: begin
                    // Si TIPO_TRANS es 0 se pasa al estado de PROCESANDO_DEPOSITO
                    if (TIPO_TRANS == 0) begin
                       estado <= PROCESANDO_DEPOSITO;
                    end else if (TIPO_TRANS == 1) begin
                    // Si TIPO_TRANS es 1 se pasa al estado de PROCESANDO_RETIRO
                       estado <= PROCESANDO_RETIRO;
                    end else begin
                    	// Si TIPO_TRANS es distinto de 0 o 1 se devuelve a ESPERANDO_TARJETA	
                       estado <= ESPERANDO_TARJETA;
                    end
                end

                PROCESANDO_DEPOSITO: begin
                    if (MONTO_STB) begin
                        // Se guarda el monto a depositar en BALANCE_ACTUALIZADO
                        BALANCE_ACTUALIZADO <= BALANCE_INICIAL + MONTO;
                        BALANCE_STB <= 1;
                        estado <= FIN;
                    end else begin
                        estado <= PROCESANDO_DEPOSITO;
                    end
                end

                PROCESANDO_RETIRO: begin
                    if (MONTO_STB) begin
                        // Se verifica si MONTO es mayor a BALANCE_ACTUALIZADO
                        if (MONTO > BALANCE_ACTUALIZADO) begin
                            // Se activa la salida de FONDOS_INSUFICIENTES
                            FONDOS_INSUFICIENTES <= 1;
                            BALANCE_STB <= 1;
                            estado <= FIN;
                        end else begin
                            // Se actualiza BALANCE_ACTUALIZADO al ser mayor a MONTO
                            BALANCE_ACTUALIZADO  <= BALANCE_ACTUALIZADO - MONTO;
                            BALANCE_STB <= 1;
                            ENTREGAR_DINERO <= 1;
                            estado <= FIN;
                        end
                    end else begin
                        estado <= PROCESANDO_RETIRO;
                    end
                end

                // Estado final del sistema que regresa todo al inicio
                FIN: begin
                    if (BALANCE_STB) begin
                        cantidad_digitos        <= 0;
                        intentos_fallidos       <= 0;
                        PIN_ACTUAL              <= 0;
                        estado                  <= ESPERANDO_TARJETA;
                        ADVERTENCIA             <= 0;
                        BLOQUEO                 <= 0;
                        BALANCE_STB             <= 0;
                        ENTREGAR_DINERO         <= 0;
                        PIN_INCORRECTO          <= 0;
                        FONDOS_INSUFICIENTES    <= 0;
                    
                    end else begin
                        estado <= FIN;
                    end
                end
                    
                // Mantiene el sistema bloqueado hasta obtener RESET = 0 y RESET = 1
                BLOQUEADO: begin
                    if (!RESET) begin
                        estado <= ESPERANDO_TARJETA;
                    end else begin
                    	estado <= BLOQUEADO;
                    end 
                end
            endcase
        end
    end

endmodule

Tarea1/Testbench.v
module Testbench;

    // Señales de entrada en Cajero.v
    wire        CLK;
    wire        RESET;
    wire        TARJETA_RECIBIDA;
    wire        DIGITO_STB;
    wire        TIPO_TRANS;
    wire        MONTO_STB;
    wire [15:0] PIN_CORRECTO;
    wire [3:0]  DIGITO;
    wire [63:0] BALANCE_INICIAL;
    wire [31:0] MONTO;

    // Señales de salida
    wire [63:0] BALANCE_ACTUALIZADO;
    wire        ADVERTENCIA;
    wire        BLOQUEO;
    wire        BALANCE_STB;
    wire        ENTREGAR_DINERO;
    wire        PIN_INCORRECTO;
    wire        FONDOS_INSUFICIENTES;

    // Instancia del DUT
    Cajero dut (
        .CLK(CLK),
        .RESET(RESET),
        .TARJETA_RECIBIDA(TARJETA_RECIBIDA),
        .PIN_CORRECTO(PIN_CORRECTO),
        .DIGITO(DIGITO),
        .DIGITO_STB(DIGITO_STB),
        .TIPO_TRANS(TIPO_TRANS),
        .BALANCE_INICIAL(BALANCE_INICIAL),
        .MONTO(MONTO),
        .MONTO_STB(MONTO_STB),
        .BALANCE_ACTUALIZADO(BALANCE_ACTUALIZADO),
        .ADVERTENCIA(ADVERTENCIA),
        .BLOQUEO(BLOQUEO),
        .BALANCE_STB(BALANCE_STB),
        .ENTREGAR_DINERO(ENTREGAR_DINERO),
        .PIN_INCORRECTO(PIN_INCORRECTO),
        .FONDOS_INSUFICIENTES(FONDOS_INSUFICIENTES)
    );

    // Instancia del tester (driver)
    tester driver (
        .CLK(CLK),
        .RESET(RESET),
        .TARJETA_RECIBIDA(TARJETA_RECIBIDA),
        .DIGITO_STB(DIGITO_STB),
        .TIPO_TRANS(TIPO_TRANS),
        .MONTO_STB(MONTO_STB),
        .PIN_CORRECTO(PIN_CORRECTO),
        .DIGITO(DIGITO),
        .BALANCE_INICIAL(BALANCE_INICIAL),
        .MONTO(MONTO)
    );

    // Monitoreo y dumping
    initial begin
        $dumpfile("cajero.vcd");
        $dumpvars(0, Testbench);

        $monitor("T=%0t | PIN=%h | BALANCE_INICIAL=%0d | BALANCE_ACTUALIZADO=%0d | ADVERTENCIA=%b | BLOQUEO=%b | PIN_INCORRECTO=%b | FONDOS_INSUFICIENTES=%b",
                 $time, PIN_CORRECTO, BALANCE_INICIAL, BALANCE_ACTUALIZADO,
                 ADVERTENCIA, BLOQUEO, PIN_INCORRECTO, FONDOS_INSUFICIENTES);
    end

endmodule

Tarea1/cajero.vcd
$date
	Tue Sep  9 09:52:32 2025
$end
$version
	Icarus Verilog
$end
$timescale
	1s
$end
$scope module Testbench $end
$var wire 1 ! TIPO_TRANS $end
$var wire 1 " TARJETA_RECIBIDA $end
$var wire 1 # RESET $end
$var wire 1 $ PIN_INCORRECTO $end
$var wire 16 % PIN_CORRECTO [15:0] $end
$var wire 1 & MONTO_STB $end
$var wire 32 ' MONTO [31:0] $end
$var wire 1 ( FONDOS_INSUFICIENTES $end
$var wire 1 ) ENTREGAR_DINERO $end
$var wire 1 * DIGITO_STB $end
$var wire 4 + DIGITO [3:0] $end
$var wire 1 , CLK $end
$var wire 1 - BLOQUEO $end
$var wire 1 . BALANCE_STB $end
$var wire 64 / BALANCE_INICIAL [63:0] $end
$var wire 64 0 BALANCE_ACTUALIZADO [63:0] $end
$var wire 1 1 ADVERTENCIA $end
$scope module dut $end
$var wire 1 ! TIPO_TRANS $end
$var wire 1 " TARJETA_RECIBIDA $end
$var wire 1 # RESET $end
$var wire 16 2 PIN_CORRECTO [15:0] $end
$var wire 1 & MONTO_STB $end
$var wire 32 3 MONTO [31:0] $end
$var wire 1 * DIGITO_STB $end
$var wire 4 4 DIGITO [3:0] $end
$var wire 1 , CLK $end
$var wire 64 5 BALANCE_INICIAL [63:0] $end
$var reg 1 1 ADVERTENCIA $end
$var reg 64 6 BALANCE_ACTUALIZADO [63:0] $end
$var reg 1 . BALANCE_STB $end
$var reg 1 - BLOQUEO $end
$var reg 1 ) ENTREGAR_DINERO $end
$var reg 1 ( FONDOS_INSUFICIENTES $end
$var reg 16 7 PIN_ACTUAL [15:0] $end
$var reg 1 $ PIN_INCORRECTO $end
$var reg 2 8 cantidad_digitos [1:0] $end
$var reg 3 9 estado [2:0] $end
$var reg 2 : intentos_fallidos [1:0] $end
$upscope $end
$scope module test $end
$var reg 64 ; BALANCE_INICIAL [63:0] $end
$var reg 1 , CLK $end
$var reg 4 < DIGITO [3:0] $end
$var reg 1 * DIGITO_STB $end
$var reg 32 = MONTO [31:0] $end
$var reg 1 & MONTO_STB $end
$var reg 16 > PIN_CORRECTO [15:0] $end
$var reg 1 # RESET $end
$var reg 1 " TARJETA_RECIBIDA $end
$var reg 1 ! TIPO_TRANS $end
$upscope $end
$upscope $end
$enddefinitions $end
#0
$dumpvars
b11010101100110 >
b0 =
b0 <
b0 ;
bx :
bx 9
bx 8
bx 7
bx 6
b0 5
b0 4
b0 3
b11010101100110 2
x1
bx 0
b0 /
x.
x-
0,
b0 +
0*
x)
x(
b0 '
0&
b11010101100110 %
x$
0#
0"
0!
$end
#2
b0 0
b0 6
0)
0(
0.
0-
01
0$
b0 :
b0 7
b0 8
b0 9
1,
#4
0,
#6
1,
#8
0,
1#
#10
1,
#12
0,
1"
#14
b1 9
1,
#16
0,
#18
1,
#20
0,
#22
1,
#24
0,
#26
1,
#28
0,
#30
1,
#32
0,
0"
#34
1,
#36
0,
b11 +
b11 4
b11 <
#37
1*
#38
b1 8
b11000000000000 7
1,
#40
0,
0*
#42
1,
#44
0,
b101 +
b101 4
b101 <
#45
1*
#46
b10 8
b11010100000000 7
1,
#48
0,
0*
#50
1,
#52
0,
b110 +
b110 4
b110 <
#53
1*
#54
b11 8
b11010101100000 7
1,
#56
0,
0*
#58
1,
#60
0,
#61
1*
#62
b10 9
b0 8
b11010101100110 7
1,
#64
0,
0*
#66
b11 9
1,
#68
0,
#70
b100 9
1,
b10011100010000 '
b10011100010000 3
b10011100010000 =
#72
0,
1&
#74
b110 9
1.
b10011100010000 0
b10011100010000 6
1,
#76
0,
0&
#78
0.
b0 9
b0 7
1,
#80
0,
1"
#82
b1 9
1,
#84
0,
#86
1,
#88
0,
#90
1,
#92
0,
#94
1,
#96
0,
#98
1,
#100
0,
0"
#102
1,
#104
0,
b11 +
b11 4
b11 <
#106
1,
#108
0,
1*
#110
b1 8
b11000000000000 7
1,
#112
0,
0*
#114
1,
#116
0,
b101 +
b101 4
b101 <
#118
1,
#120
0,
1*
#122
b10 8
b11010100000000 7
1,
#124
0,
0*
#126
1,
#128
0,
b110 +
b110 4
b110 <
#130
1,
#132
0,
1*
#134
b11 8
b11010101100000 7
1,
#136
0,
0*
#138
1,
#140
0,
#142
1,
#144
0,
1*
#146
b10 9
b0 8
b11010101100110 7
1,
#148
0,
0*
#150
b11 9
1,
#152
0,
1!
#154
b101 9
1,
#156
0,
b1101101011000 '
b1101101011000 3
b1101101011000 =
#158
1,
#160
0,
1&
#162
b110 9
1)
1.
b101110111000 0
b101110111000 6
1,
#164
0,
0&
#166
0)
0.
b0 9
b0 7
1,
#168
0,
#170
1,
#172
0,
1"
#174
b1 9
1,
#176
0,
#178
1,
#180
0,
#182
1,
#184
0,
#186
1,
#188
0,
#190
1,
#192
0,
0"
#194
1,
#196
0,
b11 +
b11 4
b11 <
#198
1,
#200
0,
1*
#202
b1 8
b11000000000000 7
1,
#204
0,
0*
#206
1,
#208
0,
b101 +
b101 4
b101 <
#210
1,
#212
0,
1*
#214
b10 8
b11010100000000 7
1,
#216
0,
0*
#218
1,
#220
0,
b110 +
b110 4
b110 <
#222
1,
#224
0,
1*
#226
b11 8
b11010101100000 7
1,
#228
0,
0*
#230
1,
#232
0,
b1 +
b1 4
b1 <
#234
1,
#236
0,
1*
#238
b10 9
b0 8
b11010101100001 7
1,
#240
0,
0*
#242
b1 9
b1 :
1,
#244
0,
#246
1$
1,
#248
0,
1*
#250
b1 8
b1010101100001 7
1,
#252
0,
0*
#254
1,
#256
0,
#258
1,
#260
0,
1*
#262
b10 8
b1000101100001 7
1,
#264
0,
0*
#266
1,
#268
0,
#270
1,
#272
0,
1*
#274
b11 8
b1000100010001 7
1,
#276
0,
0*
#278
1,
#280
0,
#282
1,
#284
0,
1*
#286
b10 9
b0 8
1,
#288
0,
0*
#290
b1 9
b10 :
1,
#292
0,
#294
0$
11
1,
#296
0,
1*
#298
b1 8
1,
#300
0,
0*
#302
1,
#304
0,
b101 +
b101 4
b101 <
#306
1,
#308
0,
1*
#310
b10 8
b1010100010001 7
1,
#312
0,
0*
#314
1,
#316
0,
b11 +
b11 4
b11 <
#318
1,
#320
0,
1*
#322
b11 8
b1010100110001 7
1,
#324
0,
0*
#326
1,
#328
0,
b100 +
b100 4
b100 <
#330
1,
#332
0,
1*
#334
b10 9
b0 8
b1010100110100 7
1,
#336
0,
0*
#338
b1 9
b11 :
1,
#340
0,
#342
b111 9
1-
01
1,
#344
0,
#346
1,
#348
0,
#350
1,
#352
0,
#354
1,
#356
0,
0#
#358
b0 0
b0 6
0-
b0 :
b0 7
b0 9
1,
#360
0,
#362
1,
#364
0,
1#
#366
1,
#368
0,
#370
1,
#372
0,
#374
b1 9
1,
1"
#376
0,
#378
1,
#380
0,
#382
1,
#384
0,
#386
1,
#388
0,
#390
1,
#392
0,
#394
1,
0"
#396
0,
#398
1,
b11 +
b11 4
b11 <
#400
0,
#402
b1 8
b11000000000000 7
1,
1*
#404
0,
#406
1,
0*
#408
0,
#410
1,
b101 +
b101 4
b101 <
#412
0,
#414
b10 8
b11010100000000 7
1,
1*
#416
0,
#418
1,
0*
#420
0,
#422
1,
b110 +
b110 4
b110 <
#424
0,
#426
b11 8
b11010101100000 7
1,
1*
#428
0,
#430
1,
0*
#432
0,
#434
1,
#436
0,
#438
b10 9
b0 8
b11010101100110 7
1,
1*
#440
0,
#442
b11 9
1,
0*
#444
0,
#446
b101 9
1,
#448
0,
#450
1,
b11011011101110100000 '
b11011011101110100000 3
b11011011101110100000 =
#452
0,
#454
b110 9
1.
1(
1,
1&
#456
0,
#458
0(
0.
b0 9
b0 7
1,
0&
