Tarea1/Tester.v
module tester(
    output reg CLK,
    output reg RESET,
    output reg TARJETA_RECIBIDA,
    output reg DIGITO_STB,
    output reg TIPO_TRANS,
    output reg MONTO_STB,
    output reg [15:0] PIN_CORRECTO,
    output reg [3:0] DIGITO,
    output reg [63:0] BALANCE_INICIAL,
    output reg [31:0] MONTO
);

    initial CLK = 0;
    always #2 CLK = ~CLK;

    initial begin
        // Inicializacion de senales
        RESET = 0;
        TARJETA_RECIBIDA = 0;
        DIGITO_STB = 0;
        TIPO_TRANS = 0;
        MONTO_STB = 0;
        PIN_CORRECTO = 16'd0;
        DIGITO = 4'd0;
        BALANCE_INICIAL = 64'd0;
        MONTO = 32'd0;

        PIN_CORRECTO = 16'b0011010101100110; // PIN 3566
        BALANCE_INICIAL = 64'd10000;
        MONTO = 32'd0;
        #4;

//-----------------------------INICIO DE PRUEBA DE DEPOSITO EXITOSO------------------------------------------
        #8 RESET = 1; //Se libera sistema
        #4 TARJETA_RECIBIDA = 1; // Se recibe la tarjeta
        #4 TARJETA_RECIBIDA = 0; // Se deja de recibir la tarjeta
        #4 DIGITO = 4'b0011; // Se recibe el primer digito
        #4 DIGITO_STB = 1; // Se indica que el digito fue recibido
        #4 DIGITO_STB = 0; // Se deja de indicar que el digito fue recibido
        #4 DIGITO = 4'b0101; // Se recibe el segundo digito
        #4 DIGITO_STB = 1; // Se indica que el digito fue recibido
        #4 DIGITO_STB = 0; // Se deja de indicar que el digito fue recibido
        #4 DIGITO = 4'b0110; // Se recibe el tercer digito  
        #4 DIGITO_STB = 1; // Se indica que el digito fue recibido
        #4 DIGITO_STB = 0; // Se deja de indicar que el digito fue recibido
        #4 DIGITO = 4'b0110; // Se recibe el cuarto digito
        #4 DIGITO_STB = 1; // Se indica que el digito fue recibido
        #4 DIGITO_STB = 0; // Se deja de indicar que el digito fue recibido
        #4 TIPO_TRANS = 0; //Deposito
        #4 MONTO = 32'd10000; // Se recibe el monto a depositar
        #4 MONTO_STB = 1; // Se indica que el monto fue recibido
        #4 MONTO_STB = 0; // Se deja de indicar que el monto fue recibido
//-------------------------------FIN PRUEBA DE DEPOSITO EXITOSO-------------------------------------------

//-------------------------------INICIO DE PRUEBA DE RETIRO EXITOSO---------------------------------------        
	    #4 TARJETA_RECIBIDA = 1; // Se recibe la tarjeta
        #4 TARJETA_RECIBIDA = 0; // Se deja de recibir la tarjeta
        #4 DIGITO = 4'b0011; // Se recibe el primer digito
        #4 DIGITO_STB = 1; // Se indica que el digito fue recibido
        #4 DIGITO_STB = 0; // Se deja de indicar que el digito fue recibido
        #4 DIGITO = 4'b0101; // Se recibe el segundo digito
        #4 DIGITO_STB = 1; // Se indica que el digito fue recibido
        #4 DIGITO_STB = 0; // Se deja de indicar que el digito fue recibido
        #4 DIGITO = 4'b0110; // Se recibe el tercer digito  
        #4 DIGITO_STB = 1; // Se indica que el digito fue recibido
        #4 DIGITO_STB = 0; // Se deja de indicar que el digito fue recibido
        #4 DIGITO = 4'b0110; // Se recibe el cuarto digito
        #4 DIGITO_STB = 1; // Se indica que el digito fue recibido
        #4 DIGITO_STB = 0; // Se deja de indicar que el digito fue recibido
        #4 TIPO_TRANS = 1; //Retiro
        #4 MONTO = 32'd7000; // Se recibe el monto a retirar
        #4 MONTO_STB = 1; // Se indica que el monto fue recibido
        #4 MONTO_STB = 0; // Se deja de indicar que el monto fue recibido
//--------------------------------FIN PRUEBA DE RETIRO EXITOSO------------------------------------------

//--------------------------------PRUEBA DE PIN INCORRECTO----------------------------------------------        
        #6 TARJETA_RECIBIDA = 1; // Se recibe la tarjeta
        #4 TARJETA_RECIBIDA = 0; // Se deja de recibir la tarjeta
        #4 DIGITO = 4'b0011; // Se recibe el primer digito
        #4 DIGITO_STB = 1; // Se indica que el digito fue recibido
        #4 DIGITO_STB = 0; // Se deja de indicar que el digito fue recibido
        #4 DIGITO = 4'b0101; // Se recibe el segundo digito
        #4 DIGITO_STB = 1; // Se indica que el digito fue recibido
        #4 DIGITO_STB = 0; // Se deja de indicar que el digito fue recibido     
        #4 DIGITO = 4'b0110; // Se recibe el tercer digito
        #4 DIGITO_STB = 1; // Se indica que el digito fue recibido
        #4 DIGITO_STB = 0; // Se deja de indicar que el digito fue recibido
        #4 DIGITO = 4'b0001; // Se recibe el cuarto digito
        #4 DIGITO_STB = 1; // Se indica que el digito fue recibido
        #4 DIGITO_STB = 0; // Se deja de indicar que el digito fue recibido
        #4 DIGITO = 4'b0001; // Se recibe el primer digito
        #4 DIGITO_STB = 1; // Se indica que el digito fue recibido
        #4 DIGITO_STB = 0; // Se deja de indicar que el digito fue recibido
        #4 DIGITO = 4'b0001; // Se recibe el segundo digito
        #4 DIGITO_STB = 1; // Se indica que el digito fue recibido
        #4 DIGITO_STB = 0; // Se deja de indicar que el digito fue recibido     
        #4 DIGITO = 4'b0001; // Se recibe el tercer digito
        #4 DIGITO_STB = 1; // Se indica que el digito fue recibido
        #4 DIGITO_STB = 0; // Se deja de indicar que el digito fue recibido
        #4 DIGITO = 4'b0001; // Se recibe el cuarto digito
        #4 DIGITO_STB = 1; // Se indica que el digito fue recibido
        #4 DIGITO_STB = 0; // Se deja de indicar que el digito fue recibido  
        #4 DIGITO = 4'b0001; // Se recibe el primer digito
        #4 DIGITO_STB = 1; // Se indica que el digito fue recibido
        #4 DIGITO_STB = 0; // Se deja de indicar que el digito fue recibido
        #4 DIGITO = 4'b0101; // Se recibe el segundo digito
        #4 DIGITO_STB = 1; // Se indica que el digito fue recibido
        #4 DIGITO_STB = 0; // Se deja de indicar que el digito fue recibido     
        #4 DIGITO = 4'b0011; // Se recibe el tercer digito
        #4 DIGITO_STB = 1; // Se indica que el digito fue recibido
        #4 DIGITO_STB = 0; // Se deja de indicar que el digito fue recibido
        #4 DIGITO = 4'b0100; // Se recibe el cuarto digito
        #4 DIGITO_STB = 1; // Se indica que el digito fue recibido
        #4 DIGITO_STB = 0; // Se deja de indicar que el digito fue recibido  
//-------------------------------FIN PRUEBA PIN INCORRECTO----------------------------------------------

//------------------------------SALIR DEL ESTADO DE BLOQUEO -------------------------
        #4 RESET = 0; // Se pone Reset en 0
        #4 RESET = 1; // Se pone Reset en 1
        #8 TARJETA_RECIBIDA = 1; // Se regresa a esperar la tarjeta
        #4 TARJETA_RECIBIDA = 0; // Se deja de recibir la tarjeta
        #4 DIGITO = 4'b0011; // Se recibe el primer digito
        #4 DIGITO_STB = 1; // Se indica que el digito fue recibido
        #4 DIGITO_STB = 0; // Se deja de indicar que el digito fue recibido
        #4 DIGITO = 4'b0101; // Se recibe el segundo digito
        #4 DIGITO_STB = 1; // Se indica que el digito fue recibido
        #4 DIGITO_STB = 0; // Se deja de indicar que el digito fue recibido
        #4 DIGITO = 4'b0110; // Se recibe el tercer digito  
        #4 DIGITO_STB = 1; // Se indica que el digito fue recibido
        #4 DIGITO_STB = 0; // Se deja de indicar que el digito fue recibido
        #4 DIGITO = 4'b0110; // Se recibe el cuarto digito
        #4 DIGITO_STB = 1; // Se indica que el digito fue recibido
        #4 DIGITO_STB = 0; // Se deja de indicar que el digito fue recibido
        #4 TIPO_TRANS = 0; //Deposito
        #4 MONTO = 32'd10000; // Se recibe el monto a depositar
        #4 MONTO_STB = 1; // Se indica que el monto fue recibido
        #4 MONTO_STB = 0; // Se deja de indicar que el monto fue recibido    
//----------------------FIN DE ACCION EN ESTADO DE BLOQUEO--------------------------------------------

//----------------------INICIO DE PRUEBA DE RETIRO FALLIDO--------------------------------------------
        #4 TARJETA_RECIBIDA = 1; // Se recibe la tarjeta
        #4 TARJETA_RECIBIDA = 0; // Se deja de recibir la tarjeta
        #4 DIGITO = 4'b0011; // Se recibe el primer digito
        #4 DIGITO_STB = 1; // Se indica que el digito fue recibido
        #4 DIGITO_STB = 0; // Se deja de indicar que el digito fue recibido
        #4 DIGITO = 4'b0101; // Se recibe el segundo digito
        #4 DIGITO_STB = 1; // Se indica que el digito fue recibido
        #4 DIGITO_STB = 0; // Se deja de indicar que el digito fue recibido
        #4 DIGITO = 4'b0110; // Se recibe el tercer digito  
        #4 DIGITO_STB = 1; // Se indica que el digito fue recibido
        #4 DIGITO_STB = 0; // Se deja de indicar que el digito fue recibido
        #4 DIGITO = 4'b0110; // Se recibe el cuarto digito
        #4 DIGITO_STB = 1; // Se indica que el digito fue recibido
        #4 DIGITO_STB = 0; // Se deja de indicar que el digito fue recibido
        #4 TIPO_TRANS = 1; //Retiro
        #4 MONTO = 32'd900000; // Se recibe el monto a retirar
        #4 MONTO_STB = 1; // Se indica que el monto fue recibido
        #4 MONTO_STB = 0; // Se deja de indicar que el monto fue recibido
//--------------------------------FIN PRUEBA DE RETIRO FALLIDO-------------------------------------------

        $finish;
    end
endmodule

Tarea1/Cajero.v
module Cajero (
    input CLK,
    input RESET,
    input TARJETA_RECIBIDA,
    input [15:0] PIN_CORRECTO, 
    input [3:0] DIGITO,
    input DIGITO_STB,
    input TIPO_TRANS,
    input [31:0] MONTO,
    input MONTO_STB,
    input [63:0] BALANCE_INICIAL,

    output reg [63:0] BALANCE_ACTUALIZADO,
    output reg BALANCE_STB,
    output reg ENTREGAR_DINERO,
    output reg FONDOS_INSUFICIENTES,
    output reg PIN_INCORRECTO,
    output reg ADVERTENCIA,
    output reg BLOQUEO
    );

    reg [1:0] intentos_fallidos;
    reg [15:0] PIN_ACTUAL;
    reg [2:0] estado;
    reg [1:0] cantidad_digitos;
    reg casi_bloqueado;


    localparam ESPERANDO_TARJETA      = 3'b000, // Esperando Tarjeta
               INGRESANDO_PIN         = 3'b001, // EL usuario esta ingresando el PIN 
               ANALIZANDO_PIN         = 3'b010, // Se verifica si el PIN es correcto
               DETERMINAR_TRANSACCION = 3'b011, // El usuario elige entre retiro o depósito
               PROCESANDO_DEPOSITO    = 3'b100, // Se procesa depósito
               PROCESANDO_RETIRO      = 3'b101, // Se procesa retiro
               FIN                    = 3'b110, // Finaliza transacción
               BLOQUEADO              = 3'b111; // Tarjeta bloqueda por intentos fallidos

    always @(posedge CLK) begin
        if (!RESET) begin // si reset = 0 se inicializan todas las variables
            estado                  <= ESPERANDO_TARJETA;
	        cantidad_digitos        <= 0;
	        PIN_ACTUAL              <= 0;

	        intentos_fallidos       <= 0;
            PIN_INCORRECTO          <= 0;
            ADVERTENCIA             <= 0;
            BLOQUEO                 <= 0;
            casi_bloqueado	        <= 0;

            BALANCE_ACTUALIZADO     <= 0;
            BALANCE_STB             <= 0;
            FONDOS_INSUFICIENTES    <= 0;
            ENTREGAR_DINERO         <= 0;

         
        end else begin // si reset = 1
            case (estado)
                // El sistema está esperando la tarjeta
		        ESPERANDO_TARJETA: begin
    		    // Si la señal TARJETA_RECIBIDA está activa (la tarjeta fue insertada)
    		    // Cambiar al estado de INGRESANDO_PIN
    		        if (TARJETA_RECIBIDA) begin
        		        estado <= INGRESANDO_PIN;
    		        end else begin
                    // Si no hay tarjeta, permanecer en ESPERANDO_TARJETA
        		        estado <= ESPERANDO_TARJETA;
    	            end
		        end

                INGRESANDO_PIN: begin
                    // si hay 2 intentos fallidos se da una advertencia
                    if (intentos_fallidos == 2'd2) begin 
                        ADVERTENCIA <= 1;
                    // si hay 3 intentos se bloquea
                    end else if (intentos_fallidos == 2'd3) begin
                    	// se pasa ADVERTENCIA a 0, BLOQUEO a 1 y se cambia de estado a BLOQUEADO
                        ADVERTENCIA <= 0;
                        BLOQUEO <= 1;
                        estado <= BLOQUEADO;
                    end else begin
                    	// si no sucede, se mantiene ADVERTENCIA en cero
                        ADVERTENCIA <= 0;
                    end
                    
                    // Si DIGITO_STB = 1 e intentos fallidos es menor a 3 
                    if (DIGITO_STB && (intentos_fallidos < 3)) begin
                    	// Se coloca PIN_INCORRECTO = 0
                        PIN_INCORRECTO <= 0;
                        // cantidad_digitos funciona como un contador que indica cuántos dígitos del PIN ya se han ingresado.
                        case (cantidad_digitos) 
                            // Si cantidad_digitos es 2'b00 (o sea, 0 en decimal), ejecuta lo que está en el bloque
                            2'b00: begin
                                PIN_ACTUAL[15:12] <= DIGITO;
                                // Se actualiza cantidad_digitos
                                cantidad_digitos <= cantidad_digitos + 1;
                            end
                            2'b01: begin
                                PIN_ACTUAL[11:8] <= DIGITO;
                                cantidad_digitos <= cantidad_digitos + 1;
                            end
                            2'b10: begin
                                PIN_ACTUAL[7:4] <= DIGITO;
                                cantidad_digitos <= cantidad_digitos + 1;
                            end
                            2'b11: begin
                                PIN_ACTUAL[3:0] <= DIGITO;
                                cantidad_digitos <= 0;
                                estado <= ANALIZANDO_PIN;
                            end
                        endcase

                    end else if (intentos_fallidos < 3) begin
                        estado <= INGRESANDO_PIN;
                    end
                end

                ANALIZANDO_PIN: begin
                    // Si el pin es incorrecto entonces se activa PIN_INCORRECTO
                    if (PIN_ACTUAL != PIN_CORRECTO) begin
                    	// Se suma un intento a intentos_fallidos
                        intentos_fallidos <= intentos_fallidos + 1;
                        PIN_INCORRECTO <= 1;
                        // Se devuelve al estado de INGRESANDO_PIN
                        estado <= INGRESANDO_PIN;
                    end else begin
                        estado <= DETERMINAR_TRANSACCION;
                    end
                end

                DETERMINAR_TRANSACCION: begin
                    // Si TIPO_TRANS es 0 se pasa al estado de PROCESANDO_DEPOSITO
                    if (TIPO_TRANS == 0) begin
                       estado <= PROCESANDO_DEPOSITO;
                    end else if (TIPO_TRANS == 1) begin
                    // Si TIPO_TRANS es 1 se pasa al estado de PROCESANDO_RETIRO
                       estado <= PROCESANDO_RETIRO;
                    end else begin
                    	// Si TIPO_TRANS es distinto de 0 o 1 se devuelve a ESPERANDO_TARJETA	
                       estado <= ESPERANDO_TARJETA;
                    end
                end

                PROCESANDO_DEPOSITO: begin
                    if (MONTO_STB) begin
                        BALANCE_ACTUALIZADO <= BALANCE_INICIAL + MONTO;
                        BALANCE_STB <= 1;
                        estado <= FIN;
                    end else begin
                        estado <= PROCESANDO_DEPOSITO;
                    end
                end

                PROCESANDO_RETIRO: begin
                    if (MONTO_STB) begin
                        // Se verifica si MONTO es mayor a BALANCE_INICIAL
                        if (MONTO > BALANCE_INICIAL) begin
                            FONDOS_INSUFICIENTES <= 1;
                            BALANCE_STB <= 1;
                            estado <= FIN;
                        end else begin
                            BALANCE_ACTUALIZADO  <= BALANCE_INICIAL - MONTO;
                            BALANCE_STB <= 1;
                            ENTREGAR_DINERO <= 1;
                            estado <= FIN;
                        end
                    end else begin
                        estado <= PROCESANDO_RETIRO;
                    end
                end

                FIN: begin
                    if (BALANCE_STB) begin
                        cantidad_digitos        <= 0;
                        intentos_fallidos       <= 0;
                        PIN_ACTUAL              <= 0;
                        estado                  <= ESPERANDO_TARJETA;
                        BALANCE_ACTUALIZADO     <= 0;
                        ADVERTENCIA             <= 0;
                        BLOQUEO                 <= 0;
                        BALANCE_STB             <= 0;
                        ENTREGAR_DINERO         <= 0;
                        PIN_INCORRECTO          <= 0;
                        FONDOS_INSUFICIENTES    <= 0;
                    
                    end else begin
                        estado <= FIN;
                    end
                end
                    
                // Mantiene el sistema bloqueado hasta obtener RESET = 0 y RESET = 1
                BLOQUEADO: begin
                    if (!RESET) begin
                        casi_bloqueado <= 1;
                        estado <= BLOQUEADO;
                    end else if (casi_bloqueado && RESET) begin
                    	casi_bloqueado <= 0;
                    	estado <= ESPERANDO_TARJETA;
                    end else begin
                    	estado <= BLOQUEADO;
                    end 
                end
            endcase
        end
    end

endmodule

Tarea1/Testbench.v
module Testbench;

    // Señales de entrada en Cajero.v
    wire        CLK;
    wire        RESET;
    wire        TARJETA_RECIBIDA;
    wire        DIGITO_STB;
    wire        TIPO_TRANS;
    wire        MONTO_STB;
    wire [15:0] PIN_CORRECTO;
    wire [3:0]  DIGITO;
    wire [63:0] BALANCE_INICIAL;
    wire [31:0] MONTO;

    // Señales de salida
    wire [63:0] BALANCE_ACTUALIZADO;
    wire        ADVERTENCIA;
    wire        BLOQUEO;
    wire        BALANCE_STB;
    wire        ENTREGAR_DINERO;
    wire        PIN_INCORRECTO;
    wire        FONDOS_INSUFICIENTES;

    // Instancia del DUT
    Cajero dut (
        .CLK(CLK),
        .RESET(RESET),
        .TARJETA_RECIBIDA(TARJETA_RECIBIDA),
        .PIN_CORRECTO(PIN_CORRECTO),
        .DIGITO(DIGITO),
        .DIGITO_STB(DIGITO_STB),
        .TIPO_TRANS(TIPO_TRANS),
        .BALANCE_INICIAL(BALANCE_INICIAL),
        .MONTO(MONTO),
        .MONTO_STB(MONTO_STB),
        .BALANCE_ACTUALIZADO(BALANCE_ACTUALIZADO),
        .ADVERTENCIA(ADVERTENCIA),
        .BLOQUEO(BLOQUEO),
        .BALANCE_STB(BALANCE_STB),
        .ENTREGAR_DINERO(ENTREGAR_DINERO),
        .PIN_INCORRECTO(PIN_INCORRECTO),
        .FONDOS_INSUFICIENTES(FONDOS_INSUFICIENTES)
    );

    // Instancia del tester (driver)
    tester driver (
        .CLK(CLK),
        .RESET(RESET),
        .TARJETA_RECIBIDA(TARJETA_RECIBIDA),
        .DIGITO_STB(DIGITO_STB),
        .TIPO_TRANS(TIPO_TRANS),
        .MONTO_STB(MONTO_STB),
        .PIN_CORRECTO(PIN_CORRECTO),
        .DIGITO(DIGITO),
        .BALANCE_INICIAL(BALANCE_INICIAL),
        .MONTO(MONTO)
    );

    // Monitoreo y dumping
    initial begin
        $dumpfile("cajero.vcd");
        $dumpvars(0, Testbench);

        $monitor("T=%0t | PIN=%h | BALANCE_INICIAL=%0d | BALANCE_ACTUALIZADO=%0d | ADVERTENCIA=%b | BLOQUEO=%b | PIN_INCORRECTO=%b | FONDOS_INSUFICIENTES=%b",
                 $time, PIN_CORRECTO, BALANCE_INICIAL, BALANCE_ACTUALIZADO,
                 ADVERTENCIA, BLOQUEO, PIN_INCORRECTO, FONDOS_INSUFICIENTES);
    end

endmodule

Tarea1/cajero.vcd
$date
	Mon Sep  1 20:15:23 2025
$end
$version
	Icarus Verilog
$end
$timescale
	1s
$end
$scope module Testbench $end
$var wire 1 ! TIPO_TRANS $end
$var wire 1 " TARJETA_RECIBIDA $end
$var wire 1 # RESET $end
$var wire 1 $ PIN_INCORRECTO $end
$var wire 16 % PIN_CORRECTO [15:0] $end
$var wire 1 & MONTO_STB $end
$var wire 32 ' MONTO [31:0] $end
$var wire 1 ( FONDOS_INSUFICIENTES $end
$var wire 1 ) ENTREGAR_DINERO $end
$var wire 1 * DIGITO_STB $end
$var wire 4 + DIGITO [3:0] $end
$var wire 1 , CLK $end
$var wire 1 - BLOQUEO $end
$var wire 1 . BALANCE_STB $end
$var wire 64 / BALANCE_INICIAL [63:0] $end
$var wire 64 0 BALANCE_ACTUALIZADO [63:0] $end
$var wire 1 1 ADVERTENCIA $end
$scope module driver $end
$var reg 64 2 BALANCE_INICIAL [63:0] $end
$var reg 1 , CLK $end
$var reg 4 3 DIGITO [3:0] $end
$var reg 1 * DIGITO_STB $end
$var reg 32 4 MONTO [31:0] $end
$var reg 1 & MONTO_STB $end
$var reg 16 5 PIN_CORRECTO [15:0] $end
$var reg 1 # RESET $end
$var reg 1 " TARJETA_RECIBIDA $end
$var reg 1 ! TIPO_TRANS $end
$upscope $end
$scope module dut $end
$var wire 64 6 BALANCE_INICIAL [63:0] $end
$var wire 1 , CLK $end
$var wire 4 7 DIGITO [3:0] $end
$var wire 1 * DIGITO_STB $end
$var wire 32 8 MONTO [31:0] $end
$var wire 1 & MONTO_STB $end
$var wire 16 9 PIN_CORRECTO [15:0] $end
$var wire 1 # RESET $end
$var wire 1 " TARJETA_RECIBIDA $end
$var wire 1 ! TIPO_TRANS $end
$var reg 1 1 ADVERTENCIA $end
$var reg 64 : BALANCE_ACTUALIZADO [63:0] $end
$var reg 1 . BALANCE_STB $end
$var reg 1 - BLOQUEO $end
$var reg 1 ) ENTREGAR_DINERO $end
$var reg 1 ( FONDOS_INSUFICIENTES $end
$var reg 16 ; PIN_ACTUAL [15:0] $end
$var reg 1 $ PIN_INCORRECTO $end
$var reg 2 < cantidad_digitos [1:0] $end
$var reg 1 = casi_bloqueado $end
$var reg 3 > estado [2:0] $end
$var reg 2 ? intentos_fallidos [1:0] $end
$upscope $end
$upscope $end
$enddefinitions $end
#0
$dumpvars
bx ?
bx >
x=
bx <
bx ;
bx :
b11010101100110 9
b0 8
b0 7
b10011100010000 6
b11010101100110 5
b0 4
b0 3
b10011100010000 2
x1
bx 0
b10011100010000 /
x.
x-
0,
b0 +
0*
x)
x(
b0 '
0&
b11010101100110 %
x$
0#
0"
0!
$end
#2
0)
0(
0.
b0 0
b0 :
0=
0-
01
0$
b0 ?
b0 ;
b0 <
b0 >
1,
#4
0,
#6
1,
#8
0,
#10
1,
#12
0,
1#
#14
1,
#16
0,
1"
#18
b1 >
1,
#20
0,
0"
#22
1,
#24
0,
b11 +
b11 3
b11 7
#26
1,
#28
0,
1*
#30
b1 <
b11000000000000 ;
1,
#32
0,
0*
#34
1,
#36
0,
b101 +
b101 3
b101 7
#38
1,
#40
0,
1*
#42
b10 <
b11010100000000 ;
1,
#44
0,
0*
#46
1,
#48
0,
b110 +
b110 3
b110 7
#50
1,
#52
0,
1*
#54
b11 <
b11010101100000 ;
1,
#56
0,
0*
#58
1,
#60
0,
#62
1,
#64
0,
1*
#66
b10 >
b0 <
b11010101100110 ;
1,
#68
0,
0*
#70
b11 >
1,
#72
0,
#74
b100 >
1,
#76
0,
b10011100010000 '
b10011100010000 4
b10011100010000 8
#78
1,
#80
0,
1&
#82
b110 >
1.
b100111000100000 0
b100111000100000 :
1,
#84
0,
0&
#86
0.
b0 0
b0 :
b0 >
b0 ;
1,
#88
0,
1"
#90
b1 >
1,
#92
0,
0"
#94
1,
#96
0,
b11 +
b11 3
b11 7
#98
1,
#100
0,
1*
#102
b1 <
b11000000000000 ;
1,
#104
0,
0*
#106
1,
#108
0,
b101 +
b101 3
b101 7
#110
1,
#112
0,
1*
#114
b10 <
b11010100000000 ;
1,
#116
0,
0*
#118
1,
#120
0,
b110 +
b110 3
b110 7
#122
1,
#124
0,
1*
#126
b11 <
b11010101100000 ;
1,
#128
0,
0*
#130
1,
#132
0,
#134
1,
#136
0,
1*
#138
b10 >
b0 <
b11010101100110 ;
1,
#140
0,
0*
#142
b11 >
1,
#144
0,
1!
#146
b101 >
1,
#148
0,
b1101101011000 '
b1101101011000 4
b1101101011000 8
#150
1,
#152
0,
1&
#154
b110 >
1)
1.
b101110111000 0
b101110111000 :
1,
#156
0,
0&
#158
0)
0.
b0 0
b0 :
b0 >
b0 ;
1,
#160
0,
#162
b1 >
1,
1"
#164
0,
#166
1,
0"
#168
0,
#170
1,
b11 +
b11 3
b11 7
#172
0,
#174
b1 <
b11000000000000 ;
1,
1*
#176
0,
#178
1,
0*
#180
0,
#182
1,
b101 +
b101 3
b101 7
#184
0,
#186
b10 <
b11010100000000 ;
1,
1*
#188
0,
#190
1,
0*
#192
0,
#194
1,
b110 +
b110 3
b110 7
#196
0,
#198
b11 <
b11010101100000 ;
1,
1*
#200
0,
#202
1,
0*
#204
0,
#206
1,
b1 +
b1 3
b1 7
#208
0,
#210
b10 >
b0 <
b11010101100001 ;
1,
1*
#212
0,
#214
b1 >
1$
b1 ?
1,
0*
#216
0,
#218
1,
#220
0,
#222
b1 <
b1010101100001 ;
0$
1,
1*
#224
0,
#226
1,
0*
#228
0,
#230
1,
#232
0,
#234
b10 <
b1000101100001 ;
1,
1*
#236
0,
#238
1,
0*
#240
0,
#242
1,
#244
0,
#246
b11 <
b1000100010001 ;
1,
1*
#248
0,
#250
1,
0*
#252
0,
#254
1,
#256
0,
#258
b10 >
b0 <
1,
1*
#260
0,
#262
b1 >
1$
b10 ?
1,
0*
#264
0,
#266
11
1,
#268
0,
#270
b1 <
0$
1,
1*
#272
0,
#274
1,
0*
#276
0,
#278
1,
b101 +
b101 3
b101 7
#280
0,
#282
b10 <
b1010100010001 ;
1,
1*
#284
0,
#286
1,
0*
#288
0,
#290
1,
b11 +
b11 3
b11 7
#292
0,
#294
b11 <
b1010100110001 ;
1,
1*
#296
0,
#298
1,
0*
#300
0,
#302
1,
b100 +
b100 3
b100 7
#304
0,
#306
b10 >
b0 <
b1010100110100 ;
1,
1*
#308
0,
#310
b1 >
1$
b11 ?
1,
0*
#312
0,
#314
01
0$
b0 ?
b0 ;
b0 >
1,
0#
#316
0,
#318
1,
1#
#320
0,
#322
1,
#324
0,
#326
b1 >
1,
1"
#328
0,
#330
1,
0"
#332
0,
#334
1,
b11 +
b11 3
b11 7
#336
0,
#338
b1 <
b11000000000000 ;
1,
1*
#340
0,
#342
1,
0*
#344
0,
#346
1,
b101 +
b101 3
b101 7
#348
0,
#350
b10 <
b11010100000000 ;
1,
1*
#352
0,
#354
1,
0*
#356
0,
#358
1,
b110 +
b110 3
b110 7
#360
0,
#362
b11 <
b11010101100000 ;
1,
1*
#364
0,
#366
1,
0*
#368
0,
#370
1,
#372
0,
#374
b10 >
b0 <
b11010101100110 ;
1,
1*
#376
0,
#378
b11 >
1,
0*
#380
0,
#382
b100 >
1,
0!
#384
0,
#386
1,
b10011100010000 '
b10011100010000 4
b10011100010000 8
#388
0,
#390
b110 >
1.
b100111000100000 0
b100111000100000 :
1,
1&
#392
0,
#394
0.
b0 0
b0 :
b0 >
b0 ;
1,
0&
#396
0,
#398
b1 >
1,
1"
#400
0,
#402
1,
0"
#404
0,
#406
1,
b11 +
b11 3
b11 7
#408
0,
#410
b1 <
b11000000000000 ;
1,
1*
#412
0,
#414
1,
0*
#416
0,
#418
1,
b101 +
b101 3
b101 7
#420
0,
#422
b10 <
b11010100000000 ;
1,
1*
#424
0,
#426
1,
0*
#428
0,
#430
1,
b110 +
b110 3
b110 7
#432
0,
#434
b11 <
b11010101100000 ;
1,
1*
#436
0,
#438
1,
0*
#440
0,
#442
1,
#444
0,
#446
b10 >
b0 <
b11010101100110 ;
1,
1*
#448
0,
#450
b11 >
1,
0*
#452
0,
#454
b101 >
1,
1!
#456
0,
#458
1,
b11011011101110100000 '
b11011011101110100000 4
b11011011101110100000 8
#460
0,
#462
b110 >
1.
1(
1,
1&
#464
0,
#466
0(
0.
b0 >
b0 ;
1,
0&
